optionset/__init__.py
optionset/optionset.py
tests/__init__.py
tests/checkstyle.py
tests/test_optionset.py
optionset-25.1.3.dist-info/AUTHORS
optionset-25.1.3.dist-info/LICENSE
optionset-25.1.3.dist-info/METADATA
optionset-25.1.3.dist-info/WHEEL
optionset-25.1.3.dist-info/entry_points.txt
optionset-25.1.3.dist-info/top_level.txt
optionset-25.1.3.dist-info/RECORD
