Metadata-Version: 2.1
Name: optionset
Version: 25.1.3
Summary: A lightweight tool for conducting parameter studies.
Home-page: https://github.com/MattCJones/optionset
Author: Matthew C. Jones
Author-email: matt.c.jones.aoe@gmail.com
License: GPLv3
Keywords: utility,macro-processor
Classifier: Development Status :: 5 - Production/Stable
Classifier: Intended Audience :: Developers
Classifier: Intended Audience :: Information Technology
Classifier: Intended Audience :: Science/Research
Classifier: Intended Audience :: System Administrators
Classifier: License :: OSI Approved :: GNU General Public License v3 (GPLv3)
Classifier: Natural Language :: English
Classifier: Operating System :: OS Independent
Classifier: Topic :: Scientific/Engineering
Classifier: Topic :: Software Development
Classifier: Topic :: Software Development :: Interpreters
Classifier: Topic :: Software Development :: Pre-processors
Classifier: Topic :: Software Development :: User Interfaces
Classifier: Topic :: Text Processing
Classifier: Topic :: Text Processing :: General
Classifier: Topic :: Text Processing :: Indexing
Classifier: Topic :: Utilities
Classifier: Programming Language :: Python :: 3.7
Classifier: Programming Language :: Python :: 3.8
Classifier: Programming Language :: Python :: 3.9
Classifier: Programming Language :: Unix Shell
Requires-Python: >=3.7
License-File: LICENSE
License-File: AUTHORS
Requires-Dist: None
